Metadata-Version: 2.1
Name: hydrobr
Version: 0.1.1
Summary: HydroBr is an open-source package to work with Brazilian hydrometeorological time series.
Home-page: https://github.com/wallissoncarvalho/hydrobr
Author: Wallisson Moreira de Carvalho
Author-email: cmwallisson@gmail.com
License: BSD 3-Clause License
Download-URL: https://github.com/wallissoncarvalho/hydrobr/archive/0.1.1.tar.gz
Keywords: timeseries flow precipitation stages
Platform: UNKNOWN
Classifier: Development Status :: 2 - Pre-Alpha
Classifier: Environment :: Console
Classifier: Operating System :: OS Independent
Classifier: Intended Audience :: Science/Research
Classifier: Programming Language :: Python :: 3
Classifier: Programming Language :: Python :: 3.6
Classifier: Programming Language :: Python :: 3.7
Classifier: Programming Language :: Python :: 3.8
Classifier: Topic :: Scientific/Engineering
